pynut.py
pynutlib-0.1.0.dist-info/METADATA
pynutlib-0.1.0.dist-info/WHEEL
pynutlib-0.1.0.dist-info/top_level.txt
pynutlib-0.1.0.dist-info/RECORD
