Metadata-Version: 2.4
Name: pynutlib
Version: 0.1.0
Summary: Nutrition scoring library using USDA API and Streamlit
Home-page: https://github.com/traviske123nccu/pynutlib
Author: traviske123nccu
Author-email: 113351001@g.nccu.edu.tw
Classifier: Programming Language :: Python :: 3
Classifier: License :: OSI Approved :: MIT License
Classifier: Operating System :: OS Independent
Requires-Python: >=3.7
Requires-Dist: streamlit
Requires-Dist: requests
Requires-Dist: pandas
Requires-Dist: numpy
Requires-Dist: matplotlib
Dynamic: author
Dynamic: author-email
Dynamic: classifier
Dynamic: description
Dynamic: description-content-type
Dynamic: home-page
Dynamic: requires-dist
Dynamic: requires-python
Dynamic: summary
